pyRdfa/__init__.py
pyRdfa/embeddedRDF.py
pyRdfa/initialcontext.py
pyRdfa/options.py
pyRdfa/parse.py
pyRdfa/property.py
pyRdfa/rdflibparsers.py
pyRdfa/state.py
pyRdfa/termorcurie.py
pyRdfa/utils.py
pyRdfa/extras/__init__.py
pyRdfa/extras/httpheader.py
pyRdfa/host/__init__.py
pyRdfa/host/atom.py
pyRdfa/host/html5.py
pyRdfa/rdfs/__init__.py
pyRdfa/rdfs/cache.py
pyRdfa/rdfs/process.py
pyRdfa/transform/DublinCore.py
pyRdfa/transform/OpenID.py
pyRdfa/transform/__init__.py
pyRdfa/transform/lite.py
pyRdfa/transform/metaname.py
pyRdfa/transform/prototype.py
pyRdfaExtras/__init__.py
pyRdfaExtras/extras/__init__.py
pyRdfaExtras/extras/odict.py
pyRdfaExtras/serializers/XMLWriter.py
pyRdfaExtras/serializers/__init__.py
pyRdfaExtras/serializers/jsonserializer.py
pyRdfaExtras/serializers/prettyXMLserializer.py
pyRdfaExtras/serializers/prettyXMLserializer_3.py
pyRdfaExtras/serializers/prettyXMLserializer_3_2.py
pyRdfaExtras/serializers/turtleserializer.py
pyRdfa3-3.5.3.dist-info/LICENSE
pyRdfa3-3.5.3.dist-info/METADATA
pyRdfa3-3.5.3.dist-info/WHEEL
pyRdfa3-3.5.3.dist-info/entry_points.txt
pyRdfa3-3.5.3.dist-info/top_level.txt
pyRdfa3-3.5.3.dist-info/RECORD
