Metadata-Version: 1.2
Name: pyRdfa3
Version: 3.5.3
Summary: pyRdfa Libray
Home-page: UNKNOWN
Author: Ivan Herman
Author-email: ivan@w3.org
Maintainer: Ivan Herman
Maintainer-email: ivan@w3.org
License: UNKNOWN
Platform: UNKNOWN
